pipenv_setup/__init__.py
pipenv_setup/__main__.py
pipenv_setup/constants.py
pipenv_setup/inconsistency_checker.py
pipenv_setup/lockfile_parser.py
pipenv_setup/main.py
pipenv_setup/msg_formatter.py
pipenv_setup/pipfile_parser.py
pipenv_setup/setup_filler.py
pipenv_setup/setup_parser.py
pipenv_setup/setup_updater.py
pipenv_setup/res/setup_template.py
pipenv_setup-3.2.0.dist-info/LICENSE
pipenv_setup-3.2.0.dist-info/METADATA
pipenv_setup-3.2.0.dist-info/WHEEL
pipenv_setup-3.2.0.dist-info/entry_points.txt
pipenv_setup-3.2.0.dist-info/top_level.txt
pipenv_setup-3.2.0.dist-info/RECORD
