Metadata-Version: 2.1
Name: pipenv-setup
Version: 3.2.0
Summary: sync Pipfile/Pipfile.lock to setup.py
Home-page: https://github.com/Madoshakalaka/pipenv-setup
Author: Matt Yan
Author-email: syan4@ualberta.ca
License: MIT
Project-URL: Bug Reports, https://github.com/Madoshakalaka/pipenv-setup/issues
Project-URL: Say Thanks!, https://github.com/Madoshakalaka/pipenv-setup
Project-URL: Source, https://github.com/Madoshakalaka/pipenv-setup
Platform: UNKNOWN
Classifier: Development Status :: 5 - Production/Stable
Classifier: Intended Audience :: Developers
Classifier: Topic :: Software Development :: Build Tools
Classifier: License :: OSI Approved :: MIT License
Classifier: Programming Language :: Python :: 2.7
Classifier: Programming Language :: Python :: 3.5
Classifier: Programming Language :: Python :: 3.6
Classifier: Programming Language :: Python :: 3.7
Classifier: Programming Language :: Python :: 3.8
Requires-Python: >=2.6, !=3.0.*, !=3.1.*, !=3.2.*, <4
Provides-Extra: dev
Provides-Extra: black
Provides-Extra: autopep8
License-File: LICENSE
